LINCENSE
MANIFEST.in
requirements.txt
setup.cfg
setup.py
zwdx_minjiang/__init__.py
zwdx_minjiang/zwdx_minjiang_test.ipynb
zwdx_minjiang.egg-info/PKG-INFO
zwdx_minjiang.egg-info/SOURCES.txt
zwdx_minjiang.egg-info/dependency_links.txt
zwdx_minjiang.egg-info/not-zip-safe
zwdx_minjiang.egg-info/requires.txt
zwdx_minjiang.egg-info/top_level.txt
zwdx_minjiang/driver/CTP100_Dev.py
zwdx_minjiang/driver/TestItems.xml
zwdx_minjiang/driver/ZW_QCS220_20241207.py
zwdx_minjiang/driver/ZW_QCS220_DRIVER_20241207.py
zwdx_minjiang/driver/ZW_QCS220_pb2.py
zwdx_minjiang/driver/ZW_QCS220_pb2_grpc.py
zwdx_minjiang/driver/ZW_XDMA_PLL_20221230.dll
zwdx_minjiang/driver/zwdx_minjiang_test.py
zwdx_minjiang/driver/__pycache__/CTP100_Dev.cpython-310.pyc
zwdx_minjiang/driver/__pycache__/ZW_QCS220_DRIVER_20241207.cpython-310.pyc
zwdx_minjiang/driver/__pycache__/ZW_QCS220_pb2.cpython-310.pyc
zwdx_minjiang/driver/__pycache__/ZW_QCS220_pb2_grpc.cpython-310.pyc
zwdx_minjiang/driver/__pycache__/zwdx_minjiang_test.cpython-310.pyc
zwdx_minjiang/driver/__pycache__/zwdx_minjiang_tools.cpython-310.pyc
zwdx_minjiang/driver/qulab_toolbox/__init__.py
zwdx_minjiang/driver/qulab_toolbox/_version.py
zwdx_minjiang/driver/qulab_toolbox/Fit/_Fit.py
zwdx_minjiang/driver/qulab_toolbox/Fit/__init__.py
zwdx_minjiang/driver/qulab_toolbox/Fit/function.py
zwdx_minjiang/driver/qulab_toolbox/Fit/__pycache__/_Fit.cpython-310.pyc
zwdx_minjiang/driver/qulab_toolbox/Fit/__pycache__/_Fit.cpython-37.pyc
zwdx_minjiang/driver/qulab_toolbox/Fit/__pycache__/__init__.cpython-310.pyc
zwdx_minjiang/driver/qulab_toolbox/Fit/__pycache__/__init__.cpython-37.pyc
zwdx_minjiang/driver/qulab_toolbox/Fit/__pycache__/function.cpython-310.pyc
zwdx_minjiang/driver/qulab_toolbox/Fit/__pycache__/function.cpython-37.pyc
zwdx_minjiang/driver/qulab_toolbox/__pycache__/__init__.cpython-310.pyc
zwdx_minjiang/driver/qulab_toolbox/__pycache__/__init__.cpython-36.pyc
zwdx_minjiang/driver/qulab_toolbox/__pycache__/__init__.cpython-37.pyc
zwdx_minjiang/driver/qulab_toolbox/__pycache__/__init__.cpython-38.pyc
zwdx_minjiang/driver/qulab_toolbox/__pycache__/_version.cpython-310.pyc
zwdx_minjiang/driver/qulab_toolbox/utils/__init__.py
