Metadata-Version: 2.1
Name: zwdx-minjiang
Version: 1.2.0
Summary: Quantum Measurement and Control Driver
Author: zwdx
License: MIT
Keywords: instrument Master
Classifier: Natural Language :: Chinese (Simplified)
Classifier: Development Status :: 3 - Alpha
Classifier: Operating System :: OS Independent
Classifier: Programming Language :: Python :: 3.10
Classifier: Programming Language :: Python :: 3.11
Classifier: Programming Language :: Python :: 3.12
Classifier: Programming Language :: Python :: 3.13
Classifier: License :: OSI Approved :: MIT License
Classifier: Topic :: Utilities
